numpytable/__init__.py
numpytable/converter.py
numpytable-0.1.0.dist-info/LICENSE
numpytable-0.1.0.dist-info/METADATA
numpytable-0.1.0.dist-info/WHEEL
numpytable-0.1.0.dist-info/top_level.txt
numpytable-0.1.0.dist-info/RECORD
