Metadata-Version: 2.1
Name: numpytable
Version: 0.1.0
Summary: 快速将Excel复制的表格文本转换为NumPy数组
Home-page: https://github.com/Knighthood2001/numpytable
Author: knighthood2001
Author-email: 2109695291@qq.com
Classifier: Programming Language :: Python :: 3
Classifier: License :: OSI Approved :: MIT License
Classifier: Operating System :: OS Independent
Classifier: Intended Audience :: Developers
Classifier: Intended Audience :: Science/Research
Classifier: Topic :: Scientific/Engineering :: Mathematics
Requires-Python: >=3.6
License-File: LICENSE
Requires-Dist: numpy >=1.19.0
